simple_hooks/__init__.py
simple_hooks/functions.py
simple_hooks-0.1.0.dist-info/METADATA
simple_hooks-0.1.0.dist-info/WHEEL
simple_hooks-0.1.0.dist-info/RECORD
