Metadata-Version: 2.4
Name: simple-hooks
Version: 0.1.0
Summary: A hopefully simple-to-use system for enabling hooks for before and after function/method calls
Project-URL: Homepage, https://github.com/k98kurz/simple-hooks
Project-URL: Bug Tracker, https://github.com/k98kurz/simple-hooks/issues
Author-email: k98kurz <k98kurz@gmail.com>
Classifier: Development Status :: 4 - Beta
Classifier: License :: OSI Approved :: ISC License (ISCL)
Classifier: Operating System :: OS Independent
Classifier: Programming Language :: Python :: 3
Classifier: Topic :: Software Development :: Libraries
Requires-Python: >=3.10
